concrete_ml_extensions-0.2.0.dist-info/METADATA
concrete_ml_extensions-0.2.0.dist-info/WHEEL
concrete_ml_extensions-0.2.0.dist-info/licenses/LICENSE
concrete_ml_extensions.libs/libcudart-218eec4c.so.12
concrete_ml_extensions.libs/libgomp-cd2d9978.so.1
concrete_ml_extensions/__init__.py
concrete_ml_extensions/concrete_ml_extensions.cpython-311-x86_64-linux-gnu.so
concrete_ml_extensions/noise_profiles/MANIFEST.json
concrete_ml_extensions/noise_profiles/profile_inner2048_chashec7d25650e17ceb7.json
concrete_ml_extensions/noise_profiles/profile_inner4096_chashec7d25650e17ceb7.json
concrete_ml_extensions/noise_profiles/profile_inner8192_chashec7d25650e17ceb7.json
concrete_ml_extensions/utils_simulation.py
concrete_ml_extensions-0.2.0.dist-info/RECORD
