Metadata-Version: 2.4
Name: concrete-ml-extensions
Version: 0.2.0
Classifier: Programming Language :: Python
Classifier: Programming Language :: Rust
License-File: LICENSE
Summary: Private matrix multiplication library using fully homomorphic encryption
Home-Page: https://zama.ai
License: BSD-3-Clause-Clear
Requires-Python: >=3.7
